.gitignore
ArtisticLicense20.html
MANIFEST.in
README.md
callDocSphinx.sh
licenses-amendments.txt
setup.cfg
setup.py
filesysobjects/__init__.py
filesysobjects/apppaths.py
filesysobjects/configdata.py
filesysobjects/netfiles.py
filesysobjects/optionparser_fsysobj.py
filesysobjects/osdata.py
filesysobjects/paths.py
filesysobjects/pathtools.py
filesysobjects/pprint.py
filesysobjects/userdata.py
filesysobjects/plugins/__init__.py
filesysobjects/plugins/http.py
filesysobjects/plugins/smb.py
pyfilesysobjects.egg-info/PKG-INFO
pyfilesysobjects.egg-info/SOURCES.txt
pyfilesysobjects.egg-info/dependency_links.txt
pyfilesysobjects.egg-info/not-zip-safe
pyfilesysobjects.egg-info/requires.txt
pyfilesysobjects.egg-info/top_level.txt