Metadata-Version: 1.1
Name: pyfilesysobjects
Version: 0.1.29
Summary: The 'pyfilesysobjects' package provides standard conform utilities for paths of file systems and URIs.
Home-page: https://sourceforge.net/projects/pyfilesysobjects/
Author: acue
Author-email: acue_sf2@sourceforge.net
License: Artistic-License-2.0 + Forced-Fairplay-Constraints
Download-URL: https://sourceforge.net/projects/pyfilesysobjects/files/
Keywords: Filesystem Python Syntax Packages Modules Files Linenumbers Filenames Modulenames Packagenames fileobjects Objects Classes Objecttrees Classtrees inspect
Platform: Linux
Platform: Windows
Platform: darwin
Classifier: Development Status :: 3 - Alpha
Classifier: Intended Audience :: Developers
Classifier: License :: Free To Use But Restricted
Classifier: License :: OSI Approved :: Artistic License
Classifier: Natural Language :: English
Classifier: Operating System :: Microsoft :: Windows
Classifier: Operating System :: OS Independent
Classifier: Operating System :: POSIX :: BSD :: OpenBSD
Classifier: Operating System :: POSIX :: Linux
Classifier: Operating System :: MacOS :: MacOS X
Classifier: Operating System :: POSIX :: SunOS/Solaris
Classifier: Operating System :: POSIX
Classifier: Programming Language :: Python
Classifier: Programming Language :: Python :: 2
Classifier: Programming Language :: Python :: 2.7
Classifier: Programming Language :: Python :: 3
Classifier: Programming Language :: Python :: 3.5
Classifier: Programming Language :: Python :: 3.6
Classifier: Programming Language :: Unix Shell
Classifier: Topic :: Software Development :: Libraries :: Python Modules
Classifier: Topic :: Utilities
